bee/__init__.py
bee/main.py
bee_movie-4.2.0.dist-info/LICENSE
bee_movie-4.2.0.dist-info/METADATA
bee_movie-4.2.0.dist-info/WHEEL
bee_movie-4.2.0.dist-info/top_level.txt
bee_movie-4.2.0.dist-info/RECORD
