Metadata-Version: 2.1
Name: bee-movie
Version: 4.2.0
Summary: A package to easy insert the Bee Movie script into any Python project.
Home-page: https://github.com/noahgarrett/BeePython
Author: Noah Garrett
Author-email: noah.garrett@jerboatechnologies.com
License: MIT
Platform: UNKNOWN
Classifier: Programming Language :: Python :: 3
Classifier: License :: OSI Approved :: MIT License
Classifier: Operating System :: OS Independent
License-File: LICENSE
